sDNA_GH/Rhino_8_API_tests.gh
sDNA_GH/__init__.py
sDNA_GH/data_cruncher.py
sDNA_GH/gdm_from_GH_Datatree.py
sDNA_GH/launcher.py
sDNA_GH/logging_wrapper.py
sDNA_GH/main.py
sDNA_GH/options_manager.py
sDNA_GH/pyshp_wrapper.py
sDNA_GH/components/icons/Build_components.png
sDNA_GH/components/icons/Component_Names.png
sDNA_GH/components/icons/Unload_sDNA.png
sDNA_GH/components/icons/config.png
sDNA_GH/components/icons/get_Geom.png
sDNA_GH/components/icons/icon_permissions.txt
sDNA_GH/components/icons/parse_data.png
sDNA_GH/components/icons/read_User_Text.png
sDNA_GH/components/icons/read_shapefile.png
sDNA_GH/components/icons/recolour_objects.png
sDNA_GH/components/icons/sDNAAccessibilityMap.png
sDNA_GH/components/icons/sDNAGeodesics.png
sDNA_GH/components/icons/sDNAHulls.png
sDNA_GH/components/icons/sDNAIntegral.png
sDNA_GH/components/icons/sDNAIntegralFromOD.png
sDNA_GH/components/icons/sDNALearn.png
sDNA_GH/components/icons/sDNALineMeasures.png
sDNA_GH/components/icons/sDNANetRadii.png
sDNA_GH/components/icons/sDNAPredict.png
sDNA_GH/components/icons/sDNAPrepare.png
sDNA_GH/components/icons/sDNASkim.png
sDNA_GH/components/icons/sDNA_General.png
sDNA_GH/components/icons/selftest.png
sDNA_GH/components/icons/write_User_Text.png
sDNA_GH/components/icons/write_shapefile.png
sDNA_GH/components/manually_built/Geom types and counts.ghuser
sDNA_GH/components/manually_built/Get co-ordinates (with no checks first).ghuser
sDNA_GH/components/manually_built/Readme.txt.ghuser
sDNA_GH/components/manually_built/Run the Geometry checker functions.ghuser
sDNA_GH/components/manually_built/Shp_Data_Tree.ghuser
sDNA_GH/components/manually_built/Unload_sDNA.ghuser
sDNA_GH/components/manually_built/Unpack_Network_Radii.ghuser
sDNA_GH/dev_tools/__init__.py
sDNA_GH/dev_tools/dev_tools.py
sDNA_GH/dev_tools/geom_types_and_counts.py
sDNA_GH/dev_tools/get_coordinates_with_no_checks.py
sDNA_GH/dev_tools/run_the_geometry_checker_functions.py
sDNA_GH/dev_tools/unload_sDNA_GH.py
sdna_gh-3.0.5.dist-info/METADATA
sdna_gh-3.0.5.dist-info/WHEEL
sdna_gh-3.0.5.dist-info/licenses/license.md
sdna_gh-3.0.5.dist-info/RECORD
