Metadata-Version: 2.4
Name: sDNA_GH
Version: 3.0.5
Summary: sDNA is a world leading tool for Spatial Design Network Analysis.  sDNA_GH is a plug-in for Grasshopper, that runs sDNA on Rhino and Grasshopper geometry and data. 
Project-URL: Homepage, https://github.com/JamesParrott/sDNA_GH
Project-URL: Bug Tracker, https://github.com/JamesParrott/sDNA_GH/issues
Author-email: James Parrott <james.parrott@proton.me>, Crispin Cooper <sdna@cardiff.ac.uk>
License: # License
License-File: license.md
Keywords: Grasshopper,Rhino,components,control,runner,tests
Classifier: Programming Language :: Python
Requires-Python: >=2.7
Requires-Dist: anteater-gh
Requires-Dist: cheetah-gh>=0.1.10
Requires-Dist: ironpyshp
Requires-Dist: mapclassif-iron
Requires-Dist: toml-tools
